{
	"configurations" : 
	[
		{
			"directories" : 
			[
				{
					"build" : ".",
					"jsonFile" : "directory-.-Debug-f5ebdc15457944623624.json",
					"minimumCMakeVersion" : 
					{
						"string" : "3.21"
					},
					"projectIndex" : 0,
					"source" : ".",
					"targetIndexes" : 
					[
						0
					]
				}
			],
			"name" : "Debug",
			"projects" : 
			[
				{
					"directoryIndexes" : 
					[
						0
					],
					"name" : "Project_PDP_11",
					"targetIndexes" : 
					[
						0
					]
				}
			],
			"targets" : 
			[
				{
					"directoryIndex" : 0,
					"id" : "Project_PDP_11::@6890427a1f51a3e7e1df",
					"jsonFile" : "target-Project_PDP_11-Debug-60cd69be5ffacdf36fcb.json",
					"name" : "Project_PDP_11",
					"projectIndex" : 0
				}
			]
		}
	],
	"kind" : "codemodel",
	"paths" : 
	{
		"build" : "/home/igor/Math,Prog,Eng/Programming/Project PDP-11/cmake-build-debug",
		"source" : "/home/igor/Math,Prog,Eng/Programming/Project PDP-11"
	},
	"version" : 
	{
		"major" : 2,
		"minor" : 3
	}
}
